AUTHORS
CHANGES
LICENSE
MANIFEST.in
README
README.md
requirements.txt
run_tests.sh
setup.py
django_userapp/__init__.py
django_userapp/backends.py
django_userapp/request.py
django_userapp.egg-info/PKG-INFO
django_userapp.egg-info/SOURCES.txt
django_userapp.egg-info/dependency_links.txt
django_userapp.egg-info/pbr.json
django_userapp.egg-info/requires.txt
django_userapp.egg-info/setup_requires.txt
django_userapp.egg-info/top_level.txt
django_userapp/tests/__init__.py
django_userapp/tests/test_userapp.py
django_userapp/tests/userapp_fake_result.json
django_userapp/tests/userapp_sample_response.json